{
  "id": "r7_hornokrcska_zprava",
  "order": 7,
  "city": "praha",
  "junction": {
    "name": "Hornokrčská × Valtínovská",
    "district": "Praha 4 · Krč",
    "lat": 50.041067,
    "lon": 14.456387,
    "source": "OSM bake (car-sim) © OpenStreetMap"
  },
  "title": {
    "cs": "Hlavní? Spíš ne",
    "en": "Main road? Not really",
    "ru": "Главная? Вряд ли"
  },
  "hint": {
    "cs": "Jedete po průběžné ulici bez značek. Zprava vyjíždí vozidlo.",
    "en": "You drive along a through street with no signs. A vehicle pulls in from the right.",
    "ru": "Вы едете по сквозной улице без знаков. Справа выезжает автомобиль."
  },
  "view": {
    "minx": -48,
    "miny": -48,
    "maxx": 48,
    "maxy": 48
  },
  "geom": {
    "core": {
      "x": 0,
      "y": 0,
      "r": 6
    },
    "roads": [
      {
        "name": "Hornokrčská",
        "centerline": [
          [
            10.3,
            38.7
          ],
          [
            0.0,
            -0.0
          ]
        ],
        "halfW": 3.5,
        "lanes": 2,
        "oneway": false,
        "priority": false
      },
      {
        "name": "Hornokrčská",
        "centerline": [
          [
            10.3,
            38.7
          ],
          [
            0.0,
            -0.0
          ]
        ],
        "halfW": 3.5,
        "lanes": 2,
        "oneway": false,
        "priority": false
      },
      {
        "name": "Valtínovská",
        "centerline": [
          [
            0.0,
            -0.0
          ],
          [
            3.0,
            -0.9
          ],
          [
            38.4,
            -11.3
          ]
        ],
        "halfW": 3.5,
        "lanes": 2,
        "oneway": false,
        "priority": false
      },
      {
        "name": "Hornokrčská",
        "centerline": [
          [
            0.0,
            -0.0
          ],
          [
            -10.3,
            -38.7
          ]
        ],
        "halfW": 3.5,
        "lanes": 2,
        "oneway": false,
        "priority": false
      }
    ],
    "rails": [],
    "signs": [],
    "crossings": [
      {
        "center": [
          3.0,
          -0.9
        ],
        "dir": [
          0.959,
          -0.282
        ],
        "halfW": 3.5
      }
    ],
    "labels": [
      {
        "x": 6.2,
        "y": 23.2,
        "text": "Hornokrčská",
        "rot": 1.311
      },
      {
        "x": 23.0,
        "y": -6.8,
        "text": "Valtínovská",
        "rot": -0.286
      }
    ]
  },
  "actors": [
    {
      "kind": "ego",
      "path": [
        [
          12.0,
          38.2
        ],
        [
          9.0,
          28.7
        ],
        [
          6.2,
          19.1
        ],
        [
          3.5,
          9.4
        ],
        [
          0.8,
          -0.2
        ],
        [
          -1.7,
          -9.9
        ],
        [
          -4.1,
          -19.6
        ],
        [
          -6.4,
          -29.4
        ],
        [
          -8.6,
          -39.2
        ]
      ],
      "v": 7,
      "spawn": 0.0
    },
    {
      "kind": "car",
      "path": [
        [
          37.9,
          -13.0
        ],
        [
          28.9,
          -10.5
        ],
        [
          20.8,
          -9.7
        ],
        [
          13.6,
          -10.6
        ],
        [
          7.3,
          -13.0
        ],
        [
          2.0,
          -17.1
        ],
        [
          -2.5,
          -22.8
        ],
        [
          -6.0,
          -30.2
        ],
        [
          -8.6,
          -39.2
        ]
      ],
      "v": 6,
      "spawn": 0.0
    }
  ],
  "decision": {
    "t": 3.0
  },
  "question": {
    "cs": "Vaše ulice vypadá jako hlavní, ale nikde nejsou značky. Zprava přijíždí vozidlo. Jak budete pokračovat?",
    "en": "Your street looks like a main road, but there are no signs anywhere. A vehicle approaches from the right. How do you proceed?",
    "ru": "Ваша улица выглядит как главная, но знаков нигде нет. Справа приближается автомобиль. Как вы поступите?"
  },
  "options": [
    {
      "text": {
        "cs": "Jsem na hlavní, mám přednost",
        "en": "I'm on the main road, I have priority",
        "ru": "Я на главной, у меня приоритет"
      },
      "correct": false,
      "rule": "prednost_zprava"
    },
    {
      "text": {
        "cs": "Bez značek dám přednost zprava",
        "en": "No signs — I give way to the right",
        "ru": "Без знаков уступаю тому, кто справа"
      },
      "correct": true,
      "rule": "prednost_zprava"
    },
    {
      "text": {
        "cs": "Zrychlím, ať to stihnu",
        "en": "Speed up to make it",
        "ru": "Ускорюсь, чтобы успеть"
      },
      "correct": false,
      "rule": "prednost_zprava"
    }
  ],
  "explain": {
    "cs": "Pokud křižovatka není označena značkami (hlavní/vedlejší), nezáleží na tom, jak „hlavní“ ulice vypadá — platí přednost zprava. Vozidlu zprava dáte přednost.",
    "en": "If a junction isn't marked with main/side-road signs, it doesn't matter how 'main' a street looks — priority-to-the-right applies. Give way to the vehicle on the right.",
    "ru": "Если перекрёсток не обозначен знаками главной/второстепенной — неважно, насколько «главной» выглядит улица: действует «помеха справа». Уступите тому, кто справа."
  },
  "citation": "§ 22 odst. 1 z. 361/2000 Sb."
}